CHANGELOG.md
MANIFEST.in
README.md
requirements.txt
setup.py
phi/README-template.md
phi/__init__.py
phi/api.py
phi/builder.py
phi/dsl.py
phi/python_builder.py
phi/utils.py
phi/version.txt
phi.egg-info/PKG-INFO
phi.egg-info/SOURCES.txt
phi.egg-info/dependency_links.txt
phi.egg-info/top_level.txt
phi/tests/__init__.py
phi/tests/some_module.py
phi/tests/test_builders.py
phi/tests/test_dsl.py
phi/tests/test_dummy.py
phi/tests/test_examples.py
phi/tests/test_lambdas.py
phi/tests/test_nodsl.py
phi/tests/test_state.py