Metadata-Version: 1.1
Name: phi
Version: 0.6.7
Summary: Phi is a library for fluent functional programming in Python which includes a DSL + facilities to create libraries that integrate with it.
Home-page: https://github.com/cgarciae/phi
Author: Cristian Garcia
Author-email: cgarcia.e88@gmail.com
License: MIT
Download-URL: https://github.com/cgarciae/phi/tarball/0.6.7
Keywords: functional programming,DSL
Platform: UNKNOWN
